gqr/__init__.py
gqr/core/__init__.py
gqr/core/dataloader.py
gqr/core/evaluator.py
gqr-0.0.5.dist-info/METADATA
gqr-0.0.5.dist-info/WHEEL
gqr-0.0.5.dist-info/RECORD
