Metadata-Version: 2.4
Name: gqr
Version: 0.0.5
Summary: Package for Guarded Query Routing Benchmark (GQR-Bench)
Project-URL: repository, https://github.com/williambrach/gqr
Requires-Python: >=3.9
Requires-Dist: datasets>=3.5.1
Requires-Dist: pandas>=2.2.3
Requires-Dist: scikit-learn>=1.6.1
